pycopilot/__init__.py
pycopilot/auth.py
pycopilot/chat.py
pycopilot/cli.py
pycopilot/config.py
pycopilot/copilot.py
pycopilot/py.typed
pycopilot/version.py
pycopilot-0.1.6.dist-info/METADATA
pycopilot-0.1.6.dist-info/WHEEL
pycopilot-0.1.6.dist-info/entry_points.txt
pycopilot-0.1.6.dist-info/RECORD
