Metadata-Version: 2.4
Name: pycopilot
Version: 0.1.6
Summary: A command-line tool to interact with GitHub Copilot
Author-email: Dheepak Krishnamurthy <1813121+kdheepak@users.noreply.github.com>
Requires-Python: >=3.12
Requires-Dist: httpx>=0.27.0
Requires-Dist: platformdirs>=4.3.7
Requires-Dist: prompt-toolkit>=3.0.50
Requires-Dist: pydantic>=2.10.6
Requires-Dist: questionary>=2.1.0
Requires-Dist: rich>=13.9.4
Requires-Dist: typer>=0.15.2
